bbhbot/__init__.py
bbhbot/bbhbot.py
bbhbot-0.0.7.dist-info/LICENSE
bbhbot-0.0.7.dist-info/METADATA
bbhbot-0.0.7.dist-info/WHEEL
bbhbot-0.0.7.dist-info/top_level.txt
bbhbot-0.0.7.dist-info/RECORD
