Metadata-Version: 2.1
Name: bbhbot
Version: 0.0.7
Summary: A script to find and react to BBH commands in comments
Home-page: https://github.com/flaxz/bbhbot
Author: Erik Gustafsson (Team Alive) and Hive Pizza Team
Author-email: erikegse@gmail.com
Project-URL: Bug Tracker, https://github.com/flaxz/bbhbot/issues
Classifier: Programming Language :: Python :: 3
Classifier: License :: OSI Approved :: MIT License
Classifier: Operating System :: OS Independent
Requires-Python: >=3.6
License-File: LICENSE
